odoo/addons/base_bank_from_iban/README.rst
odoo/addons/base_bank_from_iban/__init__.py
odoo/addons/base_bank_from_iban/__manifest__.py
odoo/addons/base_bank_from_iban/i18n/base_bank_from_iban.pot
odoo/addons/base_bank_from_iban/i18n/es.po
odoo/addons/base_bank_from_iban/i18n/hr.po
odoo/addons/base_bank_from_iban/i18n/it.po
odoo/addons/base_bank_from_iban/i18n/nl.po
odoo/addons/base_bank_from_iban/models/__init__.py
odoo/addons/base_bank_from_iban/models/res_bank.py
odoo/addons/base_bank_from_iban/models/res_partner_bank.py
odoo/addons/base_bank_from_iban/readme/CONFIGURE.md
odoo/addons/base_bank_from_iban/readme/CONTRIBUTORS.md
odoo/addons/base_bank_from_iban/readme/DESCRIPTION.md
odoo/addons/base_bank_from_iban/readme/USAGE.md
odoo/addons/base_bank_from_iban/static/description/icon.png
odoo/addons/base_bank_from_iban/static/description/index.html
odoo/addons/base_bank_from_iban/tests/__init__.py
odoo/addons/base_bank_from_iban/tests/test_base_bank_from_iban.py
odoo/addons/base_bank_from_iban/views/res_bank_view.xml
odoo/addons/base_bank_from_iban/wizards/__init__.py
odoo/addons/base_bank_from_iban/wizards/account_setup_bank_manual_config.py
odoo_addon_base_bank_from_iban-19.0.1.0.0.2.dist-info/METADATA
odoo_addon_base_bank_from_iban-19.0.1.0.0.2.dist-info/WHEEL
odoo_addon_base_bank_from_iban-19.0.1.0.0.2.dist-info/top_level.txt
odoo_addon_base_bank_from_iban-19.0.1.0.0.2.dist-info/RECORD
