Metadata-Version: 2.1
Name: odoo-addon-base_bank_from_iban
Version: 19.0.1.0.0.2
Requires-Dist: odoo==19.0.*
Requires-Dist: schwifty==2024.4.0
Summary: Bank from IBAN
Home-page: https://github.com/OCA/community-data-files
License: AGPL-3
Author: Tecnativa, Odoo Community Association (OCA)
Author-email: support@odoo-community.org
Classifier: Programming Language :: Python
Classifier: Framework :: Odoo
Classifier: Framework :: Odoo :: 19.0
Classifier: License :: OSI Approved :: GNU Affero General Public License v3
Classifier: Development Status :: 6 - Mature
